maica/__init__.py
maica/common_schedule.py
maica/maica_http.py
maica/maica_nows.py
maica/maica_starter.py
maica/maica_ws.py
maica/test_essentials.py
maica/initializer/__init__.py
maica/initializer/gen_keys.py
maica/initializer/init_db.py
maica/initializer/init_marking.py
maica/maica_utils/__init__.py
maica/maica_utils/account_utils.py
maica/maica_utils/connection_utils.py
maica/maica_utils/container_utils.py
maica/maica_utils/get_a_sentence.py
maica/maica_utils/locater.py
maica/maica_utils/maica_utils.py
maica/maica_utils/sb_utils.py
maica/maica_utils/setting_utils.py
maica/mfocus/__init__.py
maica/mfocus/agent_modules.py
maica/mfocus/mfocus_main.py
maica/mfocus/mfocus_sfe.py
maica/mtools/__init__.py
maica/mtools/enet_scraping.py
maica/mtools/ev_scraping.py
maica/mtools/mpostal.py
maica/mtools/mspire.py
maica/mtools/nv_watcher.py
maica/mtools/post_proc.py
maica/mtools/weather_scraping.py
maica/mtools/wiki_scraping.py
maica/mtrigger/__init__.py
maica/mtrigger/mtrigger_main.py
maica/mtrigger/mtrigger_sfe.py
maica/mtrigger/trigger_class.py
mi_maica-1.1001.dist-info/LICENSE.txt
mi_maica-1.1001.dist-info/METADATA
mi_maica-1.1001.dist-info/WHEEL
mi_maica-1.1001.dist-info/entry_points.txt
mi_maica-1.1001.dist-info/top_level.txt
mi_maica-1.1001.dist-info/RECORD
