Metadata-Version: 2.1
Name: mi-maica
Version: 1.1001
Summary: MAICA Illuminator (Backend)
Home-page: https://github.com/Mon1-innovation/MAICA
Author: EdgeInfinity
Author-email: dcc@monika.love
Classifier: Programming Language :: Python :: 3
Classifier: License :: OSI Approved :: MIT License
Classifier: Operating System :: OS Independent
Requires-Python: >=3.12
License-File: LICENSE.txt
